aisfx/__init__.py
aisfx/inference.py
aisfx/preprocessing.py
aisfx/utils.py
aisfx/models/__init__.py
aisfx/models/checkpoint.pth
aisfx/models/cnn2d.py
aisfx/spectrogram/__init__.py
aisfx/spectrogram/spectrogram_essentia.py
aisfx/spectrogram/spectrogram_librosa.py
aisfx-0.1.2.dist-info/METADATA
aisfx-0.1.2.dist-info/WHEEL
aisfx-0.1.2.dist-info/licenses/LICENSE
aisfx-0.1.2.dist-info/RECORD
