Metadata-Version: 2.1
Name: aisfx
Version: 0.1.2
Summary: Representation Learning for the Automatic Indexing of Sound Effects Libraries (ISMIR 2022): Deep audio embeddings pre-trained on UCS & Non-UCS-compliant datasets.
Project-URL: Source, https://github.com/alisonbma/aisfx
Project-URL: Tracker, https://github.com/alisonbma/aisfx/issues
Author-email: Alison Bernice Ma <ama67@gatech.edu>, Alexander Lerch <alexander.lerch@gatech.edu>
License-File: LICENSE
Keywords: audio,deep,embeddings,learning,machine,pytorch,representation,sound effects library,universal category system
Classifier: Development Status :: 3 - Alpha
Classifier: Intended Audience :: Developers
Classifier: Intended Audience :: Science/Research
Classifier: License :: OSI Approved :: MIT License
Classifier: Topic :: Multimedia :: Sound/Audio :: Analysis
Requires-Dist: argparse==1.1
Requires-Dist: librosa==0.9.2
Requires-Dist: numpy==1.23.0
Requires-Dist: tqdm==4.62.3
Provides-Extra: doc
Requires-Dist: myst-parser==0.18.0; extra == 'doc'
Requires-Dist: nbsphinx==0.8.9; extra == 'doc'
Requires-Dist: numpydoc==1.4.0; extra == 'doc'
Requires-Dist: readthedocs-sphinx-search==0.1.2; extra == 'doc'
Requires-Dist: sphinx-issues==3.0.1; extra == 'doc'
Requires-Dist: sphinx-rtd-theme==1.0.0; extra == 'doc'
Requires-Dist: sphinx==5.1.1; extra == 'doc'
